ibfs/__init__.py
ibfs/__main__.py
ibfs/core.py
ibfs-0.1.0.dist-info/WHEEL
ibfs-0.1.0.dist-info/METADATA
ibfs-0.1.0.dist-info/RECORD
