Metadata-Version: 2.1
Name: ibfs
Version: 0.1.0
Summary: Mount instabase filesystem API locally
Author: Arjoonn Sharma
Author-email: arjoonn.sharma@instabase.com
Requires-Python: >=3.7,<4.0
Classifier: Programming Language :: Python :: 3
Classifier: Programming Language :: Python :: 3.7
Classifier: Programming Language :: Python :: 3.8
Classifier: Programming Language :: Python :: 3.9
Requires-Dist: PyYAML (>=6.0,<7.0)
Requires-Dist: click (>=8.0.3,<9.0.0)
Requires-Dist: fusepy (>=3.0.1,<4.0.0)
Requires-Dist: requests (>=2.27.1,<3.0.0)
Requires-Dist: tqdm (>=4.62.3,<5.0.0)
Requires-Dist: trieregex (>=1.0.0,<2.0.0)
Requires-Dist: ujson (>=5.1.0,<6.0.0)
